Metadata-Version: 2.1
Name: py-trello
Version: 0.20.1
Summary: Python wrapper around the Trello API
Home-page: https://trello.com/board/py-trello/4f145d87b2f9f15d6d027b53
Download-URL: https://github.com/sarumont/py-trello
Author: Richard Kolkovich
Author-email: richard@sigil.org
License: BSD License
Keywords: python
Classifier: Development Status :: 4 - Beta
Classifier: Intended Audience :: Developers
Classifier: License :: OSI Approved :: BSD License
Classifier: Operating System :: OS Independent
Classifier: Programming Language :: Python
Classifier: Programming Language :: Python :: 2
Classifier: Programming Language :: Python :: 2.7
Classifier: Programming Language :: Python :: 3
Classifier: Programming Language :: Python :: 3.3
License-File: LICENSE
License-File: AUTHORS.md
Requires-Dist: requests
Requires-Dist: requests-oauthlib>=0.4.1
Requires-Dist: python-dateutil
Requires-Dist: pytz
